botpy/__init__.py
botpy/api.py
botpy/audio.py
botpy/bot.py
botpy/channel.py
botpy/client.py
botpy/config.py
botpy/connection.py
botpy/errors.py
botpy/flags.py
botpy/forum.py
botpy/gateway.py
botpy/guild.py
botpy/http.py
botpy/interaction.py
botpy/json_read.py
botpy/logging.py
botpy/manage.py
botpy/message.py
botpy/reaction.py
botpy/robot.py
botpy/user.py
botpy/ext/__init__.py
botpy/ext/command_util.py
botpy/ext/channel_jump/__init__.py
botpy/ext/cog_apscheduler/__init__.py
botpy/ext/cog_yaml/__init__.py
botpy/ext/convert_color/__init__.py
botpy/types/__init__.py
botpy/types/announce.py
botpy/types/audio.py
botpy/types/channel.py
botpy/types/emoji.py
botpy/types/forum.py
botpy/types/gateway.py
botpy/types/guild.py
botpy/types/inline.py
botpy/types/interaction.py
botpy/types/message.py
botpy/types/permission.py
botpy/types/pins_message.py
botpy/types/reaction.py
botpy/types/rich_text.py
botpy/types/robot.py
botpy/types/schedule.py
botpy/types/session.py
botpy/types/user.py
bclz_qqbot-1.0.dist-info/LICENSE
bclz_qqbot-1.0.dist-info/METADATA
bclz_qqbot-1.0.dist-info/WHEEL
bclz_qqbot-1.0.dist-info/top_level.txt
bclz_qqbot-1.0.dist-info/RECORD
